anki/__init__.py
anki/errors.py
anki/control/controller.py
anki/control/scanner.py
anki/control/vehicle.py
anki/misc/const.py
anki/misc/lanes.py
anki/misc/msg_protocol.py
anki/misc/msgs.py
anki/misc/track_pieces.py
anki/misc/deprecated_alias/__init__.py
anki/misc/deprecated_alias/alias.py
py_drivesdk-1.0.3.dist-info/METADATA
py_drivesdk-1.0.3.dist-info/WHEEL
py_drivesdk-1.0.3.dist-info/top_level.txt
py_drivesdk-1.0.3.dist-info/RECORD
