Metadata-Version: 2.1
Name: py-drivesdk
Version: 1.0.3
Summary: Object oriented library for controlling Anki Overdrive vehicles
Author: Pascal Rombach, jateute, Felix Albrecht
Project-URL: Documentation, https://py-drivesdk.readthedocs.io
Project-URL: Homepage, https://github.com/HHG-TecLap/py-drivesdk
Keywords: Anki Overdrive,Anki
Classifier: Programming Language :: Python :: 3
Classifier: Programming Language :: Python :: Implementation :: CPython
Classifier: Operating System :: OS Independent
Classifier: Topic :: Education
Classifier: Topic :: Software Development :: Libraries :: Python Modules
Requires-Python: >=3.10
Requires-Dist: bleak
